orbitalsai/__init__.py
orbitalsai/async_client.py
orbitalsai/client.py
orbitalsai/exceptions.py
orbitalsai/models.py
orbitalsai/utils.py
orbitalsai-1.0.0.dist-info/licenses/LICENSE
orbitalsai-1.0.0.dist-info/METADATA
orbitalsai-1.0.0.dist-info/WHEEL
orbitalsai-1.0.0.dist-info/top_level.txt
orbitalsai-1.0.0.dist-info/RECORD
