Metadata-Version: 2.4
Name: orbitalsai
Version: 1.0.0
Summary: A simple and powerful Python SDK for the OrbitalsAI API
Home-page: https://github.com/orbitalsai/orbitalsai-python-sdk
Author: OrbitalsAI
Author-email: OrbitalsAI <support@orbitalsai.com>
Maintainer-email: OrbitalsAI <support@orbitalsai.com>
License: MIT
Project-URL: Homepage, https://github.com/orbitalsai/orbitalsai-python-sdk
Project-URL: Documentation, https://docs.orbitalsai.com
Project-URL: Repository, https://github.com/orbitalsai/orbitalsai-python-sdk
Project-URL: Bug Tracker, https://github.com/orbitalsai/orbitalsai-python-sdk/issues
Keywords: ai,transcription,audio,speech,african languages,srt,subtitles
Classifier: Development Status :: 4 - Beta
Classifier: Intended Audience :: Developers
Classifier: License :: OSI Approved :: MIT License
Classifier: Operating System :: OS Independent
Classifier: Programming Language :: Python :: 3
Classifier: Programming Language :: Python :: 3.8
Classifier: Programming Language :: Python :: 3.9
Classifier: Programming Language :: Python :: 3.10
Classifier: Programming Language :: Python :: 3.11
Classifier: Programming Language :: Python :: 3.12
Classifier: Topic :: Software Development :: Libraries :: Python Modules
Classifier: Topic :: Multimedia :: Sound/Audio :: Speech
Requires-Python: >=3.8
License-File: LICENSE
Requires-Dist: requests>=2.25.0
Requires-Dist: aiohttp>=3.8.0
Requires-Dist: python-dateutil>=2.8.0
Provides-Extra: dev
Requires-Dist: pytest>=6.0; extra == "dev"
Requires-Dist: pytest-asyncio>=0.18.0; extra == "dev"
Requires-Dist: black>=21.0; extra == "dev"
Requires-Dist: flake8>=3.9; extra == "dev"
Requires-Dist: mypy>=0.910; extra == "dev"
Dynamic: author
Dynamic: home-page
Dynamic: license-file
Dynamic: requires-python
